specialsauce/__init__.py
specialsauce/sources/__init__.py
specialsauce/sources/minetti.py
specialsauce/sources/strava.py
specialsauce/sources/trainingpeaks.py
specialsauce-0.0.2.dist-info/LICENSE
specialsauce-0.0.2.dist-info/METADATA
specialsauce-0.0.2.dist-info/WHEEL
specialsauce-0.0.2.dist-info/top_level.txt
specialsauce-0.0.2.dist-info/RECORD
